ppvideo/LICENSE
ppvideo/MANIFEST.in
ppvideo/README.md
ppvideo/__init__.py
ppvideo/main.py
ppvideo/data/k400/Kinetics-400_label_list.txt
ppvideo/paddlevideo/__init__.py
ppvideo/paddlevideo/version.py
ppvideo/paddlevideo/loader/__init__.py
ppvideo/paddlevideo/loader/builder.py
ppvideo/paddlevideo/loader/dali_loader.py
ppvideo/paddlevideo/loader/registry.py
ppvideo/paddlevideo/loader/dataset/MRI.py
ppvideo/paddlevideo/loader/dataset/MRI_SlowFast.py
ppvideo/paddlevideo/loader/dataset/__init__.py
ppvideo/paddlevideo/loader/dataset/actbert_dataset.py
ppvideo/paddlevideo/loader/dataset/asrf_dataset.py
ppvideo/paddlevideo/loader/dataset/ava_dataset.py
ppvideo/paddlevideo/loader/dataset/base.py
ppvideo/paddlevideo/loader/dataset/bmn_dataset.py
ppvideo/paddlevideo/loader/dataset/davis_dataset.py
ppvideo/paddlevideo/loader/dataset/feature.py
ppvideo/paddlevideo/loader/dataset/frame.py
ppvideo/paddlevideo/loader/dataset/ms_tcn_dataset.py
ppvideo/paddlevideo/loader/dataset/msrvtt.py
ppvideo/paddlevideo/loader/dataset/oxford.py
ppvideo/paddlevideo/loader/dataset/skeleton.py
ppvideo/paddlevideo/loader/dataset/slowfast_video.py
ppvideo/paddlevideo/loader/dataset/ucf101_skeleton.py
ppvideo/paddlevideo/loader/dataset/ucf24_dataset.py
ppvideo/paddlevideo/loader/dataset/video.py
ppvideo/paddlevideo/loader/pipelines/__init__.py
ppvideo/paddlevideo/loader/pipelines/anet_pipeline.py
ppvideo/paddlevideo/loader/pipelines/augmentations.py
ppvideo/paddlevideo/loader/pipelines/augmentations_ava.py
ppvideo/paddlevideo/loader/pipelines/compose.py
ppvideo/paddlevideo/loader/pipelines/decode.py
ppvideo/paddlevideo/loader/pipelines/decode_image.py
ppvideo/paddlevideo/loader/pipelines/decode_sampler.py
ppvideo/paddlevideo/loader/pipelines/decode_sampler_MRI.py
ppvideo/paddlevideo/loader/pipelines/mix.py
ppvideo/paddlevideo/loader/pipelines/multimodal.py
ppvideo/paddlevideo/loader/pipelines/sample.py
ppvideo/paddlevideo/loader/pipelines/sample_ava.py
ppvideo/ppvideo.egg-info/PKG-INFO
ppvideo/ppvideo.egg-info/SOURCES.txt
ppvideo/ppvideo.egg-info/dependency_links.txt
ppvideo/ppvideo.egg-info/entry_points.txt
ppvideo/ppvideo.egg-info/requires.txt
ppvideo/ppvideo.egg-info/top_level.txt
ppvideo-2.3.1.dist-info/LICENSE
ppvideo-2.3.1.dist-info/METADATA
ppvideo-2.3.1.dist-info/WHEEL
ppvideo-2.3.1.dist-info/entry_points.txt
ppvideo-2.3.1.dist-info/top_level.txt
ppvideo-2.3.1.dist-info/RECORD
