Metadata-Version: 2.1
Name: ppvideo
Version: 2.3.1
Summary: Awesome Video toolkits based on PaddlePaddle 
Home-page: https://github.com/PaddlePaddle/PaddleVideo
License: Apache License 2.0
Download-URL: https://github.com/PaddlePaddle/PaddleVideo.git
Keywords: A treasure chest for video understanding powered by PaddlePaddle.
Platform: UNKNOWN
Classifier: Intended Audience :: Developers
Classifier: Operating System :: OS Independent
Classifier: Natural Language :: Chinese (Simplified)
Classifier: Programming Language :: Python :: 3
Classifier: Programming Language :: Python :: 3.2
Classifier: Programming Language :: Python :: 3.3
Classifier: Programming Language :: Python :: 3.4
Classifier: Programming Language :: Python :: 3.5
Classifier: Programming Language :: Python :: 3.6
Classifier: Programming Language :: Python :: 3.7
Classifier: Topic :: Utilities
Requires-Dist: numpy
Requires-Dist: pandas
Requires-Dist: tqdm
Requires-Dist: PyYAML (>=5.1)
Requires-Dist: opencv-python (==4.2.0.32)
Requires-Dist: decord (==0.4.2)
Requires-Dist: av (==8.0.3)
Requires-Dist: scipy (==1.6.3)
Requires-Dist: scikit-image
